napari_nifti/__init__.py
napari_nifti/_reader.py
napari_nifti/_writer.py
napari_nifti/napari.yaml
napari_nifti-0.0.17.dist-info/LICENSE
napari_nifti-0.0.17.dist-info/METADATA
napari_nifti-0.0.17.dist-info/WHEEL
napari_nifti-0.0.17.dist-info/entry_points.txt
napari_nifti-0.0.17.dist-info/top_level.txt
napari_nifti-0.0.17.dist-info/RECORD
