Metadata-Version: 2.1
Name: napari-nifti
Version: 0.0.17
Summary: A napari plugin for reading and writing NIFTI files that have the extension .nii or .nii.gz.
Home-page: https://github.com/MIC-DKFZ/napari-nifti
Author: Karol Gotkowski
Author-email: karol.gotkowski@dkfz.de
License: Apache-2.0
Project-URL: Bug Tracker, https://github.com/MIC-DKFZ/napari-nifti/issues
Project-URL: Documentation, https://github.com/MIC-DKFZ/napari-nifti#README.md
Project-URL: Source Code, https://github.com/MIC-DKFZ/napari-nifti
Project-URL: User Support, https://github.com/MIC-DKFZ/napari-nifti/issues
Classifier: Development Status :: 2 - Pre-Alpha
Classifier: Framework :: napari
Classifier: Intended Audience :: Developers
Classifier: License :: OSI Approved :: Apache Software License
Classifier: Operating System :: OS Independent
Classifier: Programming Language :: Python
Classifier: Programming Language :: Python :: 3
Classifier: Programming Language :: Python :: 3 :: Only
Classifier: Programming Language :: Python :: 3.8
Classifier: Programming Language :: Python :: 3.9
Classifier: Programming Language :: Python :: 3.10
Classifier: Topic :: Scientific/Engineering :: Image Processing
Requires-Python: >=3.8
License-File: LICENSE
Requires-Dist: medvol
Provides-Extra: testing
Requires-Dist: tox; extra == "testing"
Requires-Dist: pytest; extra == "testing"
Requires-Dist: pytest-cov; extra == "testing"
